{
    "common": {
        "name": "awattar",
        "version": "0.0.1",
        "news": {
            "0.0.1": {
                "en": "initial release",
                "de": "Erstveröffentlichung"
            }
        },
        "title": "aWATTar",
        "titleLang": {
            "en": "aWATTar",
            "de": "aWATTar"
        },
        "desc": {
            "en": "reads out hourly prices from aWATTar",
            "de": "liest Stundenpreise von der aWATTar Website"
        },
        "authors": [
            "SirJojo69 <gtj.howe@gmx.de>"
        ],
        "keywords": [
            "PV",
            "aWATTAR"
        ],
        "license": "MIT",
        "platform": "Javascript/Node.js",
        "main": "main.js",
        "icon": "awattar.png",
        "enabled": true,
        "extIcon": "https://raw.githubusercontent.com/sirjojo69/ioBroker.awattar/master/admin/awattar.png",
        "readme": "https://github.com/sirjojo69/ioBroker.awattar/blob/master/README.md",
        "loglevel": "info",
        "mode": "daemon",
        "type": "utility",
        "compact": true,
        "connectionType": "cloud",
        "dataSource": "poll",
        "materialize": true,
        "materializeTab": true,
        "adminTab": {
            "singleton": true,
            "name": {
                "en": "aWATTar",
                "de": "aWATTar"
            },
            "link": "",
            "fa-icon": "info"
        },
        "supportCustoms": true,
        "dependencies": [
            {
                "js-controller": ">=2.0.0"
            }
        ]
    },
    "native": {
        "Marketdata URL": "https://api.awattar.de/v1/marketdata"
    },
    "objects": [],
    "instanceObjects": []
}